Metadata-Version: 1.0
Name: poncho
Version: 0.0.1
Summary: Poncho
Home-page: UNKNOWN
Author: Bülent Aldemir
Author-email: buelent@e-evolution.de
License: MIT
Platform: UNKNOWN
